mcplex/__init__.py
mcplex/cli.py
mcplex/client.py
mcplex/mcp_errors.py
mcplex/mcp_manager.py
mcplex/mcp_types.py
mcplex/utils.py
mcplex/providers/__init__.py
mcplex/providers/anthropic.py
mcplex/providers/ollama.py
mcplex/providers/openai.py
mcplex-0.1.2.dist-info/METADATA
mcplex-0.1.2.dist-info/WHEEL
mcplex-0.1.2.dist-info/entry_points.txt
mcplex-0.1.2.dist-info/top_level.txt
mcplex-0.1.2.dist-info/RECORD
