Metadata-Version: 2.4
Name: mcplex
Version: 0.1.2
Summary: A flexible and powerful Python client for Model Context Protocol (MCP) servers with advanced connection management
Author: Ichigo3766
License-Expression: MIT
Classifier: Programming Language :: Python :: 3
Classifier: Operating System :: OS Independent
Requires-Python: >=3.8
Requires-Dist: openai
Requires-Dist: mcp[cli]
Requires-Dist: python-dotenv
Requires-Dist: anthropic
Requires-Dist: ollama
Requires-Dist: jsonschema
Provides-Extra: dev
Requires-Dist: pytest; extra == "dev"
Requires-Dist: pytest-asyncio; extra == "dev"
Requires-Dist: pytest-mock; extra == "dev"
Requires-Dist: uv; extra == "dev"
Provides-Extra: demo
Requires-Dist: mcp-server-sqlite; extra == "demo"
